{
	"errno": 0,
	"data": [
		{
			"pinUrl": "img/01.jpg",
			"pinTitle": "Alfie Allen comme Theon Greyjoy et Sophie Turner",
			"pinDescription":"Game of Thrones | Saison 6 |",
			"pinAttribution":"Ice.Fire And Thrones",
			"pinSourceType" :"Film",
			"pinIdType":"1",
			"pinPiked":"true",
			"pinCreditsname":"AJ",
			"pinLike":30,
			"pinSocialitem":300,
			"pinProtrait":"img/b1.jpg",
			"width":474,
			"height":710
		},
		{
			"pinUrl": "img/02.jpg",
			"pinTitle": "quit panic! ",
			"pinDescription":"and join modeling jk jk",
			"pinAttribution":"Tumblr",
			"pinSourceType" :"Humor",
			"pinIdType":"2",
			"pinPiked":"true",
			"pinCreditsname":"AJ",
			"pinLike":30,
			"pinSocialitem":3000,
			"pinProtrait":"img/b1.jpg",
			"width":474,
			"height":823
		},
		{
			"pinUrl": "img/03.jpg",
			"pinTitle": " Bedroom Mural'",
			"pinDescription":"derection",
			"pinAttribution":"Apartment Therapy",
			"pinSourceType" :"interior design",
			"pinIdType":"3",
			"pinPiked":"true",
			"pinCreditsname":"AJ",
			"pinLike":30,
			"pinSocialitem":3000,
			"pinProtrait":"img/b1.jpg",
			"width":474,
			"height":711
		},
		{
			"pinUrl": "img/04.jpg",
			"pinTitle": "Attachment",
			"pinDescription":"ui",
			"pinAttribution":"Dribbble",
			"pinSourceType" :"UI",
			"pinIdType":"4",
			"pinPiked":"true",
			"pinCreditsname":"AJ",
			"pinLike":30,
			"pinSocialitem":3000,
			"pinProtrait":"img/b1.jpg",
			"width":426,
			"height":1115
		},
		{
			"pinUrl": "img/05.jpg",
			"pinTitle": "Lady",
			"pinDescription":"",
			"pinAttribution":"Apartment Therapy",
			"pinSourceType" :"Fashion",
			"pinIdType":"5",
			"pinPiked":"true",
			"pinCreditsname":"AJ",
			"pinLike":30,
			"pinSocialitem":3000,
			"pinProtrait":"img/b1.jpg",
			"width":474,
			"height":727
		},
		{
			"pinUrl": "img/06.jpg",
			"pinTitle": "look out",
			"pinDescription":"look out the dogs,so cute",
			"pinAttribution":"Apartment Therapy",
			"pinSourceType" :"Pat",
			"pinIdType":"6",
			"pinPiked":"true",
			"pinCreditsname":"AJ",
			"pinLike":30,
			"pinSocialitem":3000,
			"pinProtrait":"img/b1.jpg",
			"width":474,
			"height":600
		},
		{
			"pinUrl": "img/07.jpg",
			"pinTitle": "Phoebe Philo",
			"pinDescription":"photographed by David Sims in Vogue Paris...",
			"pinAttribution":"Apartment Therapy",
			"pinSourceType" :"Art & Fashion",
			"pinIdType":"7",
			"pinPiked":"true",
			"pinCreditsname":"AJ",
			"pinLike":30,
			"pinSocialitem":3000,
			"pinProtrait":"img/b1.jpg",
			"width":474,
			"height":703
		},
		{
			"pinUrl": "img/08.jpg",
			"pinTitle": "Attachment",
			"pinDescription":"Dribbble",
			"pinAttribution":"Apartment Therapy",
			"pinSourceType" :"ui",
			"pinIdType":"4",
			"pinPiked":"true",
			"pinCreditsname":"AJ",
			"pinLike":30,
			"pinSocialitem":3110,
			"pinProtrait":"img/b1.jpg",
			"width":426,
			"height":1200
		},
		{
			"pinUrl": "img/09.jpg",
			"pinTitle": "The 'Mountain Mural Bedroom Mural'",
			"pinDescription":"switch up your bedroom design with some original art",
			"pinAttribution":"Apartment Therapy",
			"pinSourceType" :"Fashion",
			"pinIdType":"5",
			"pinPiked":"true",
			"pinCreditsname":"AJ",
			"pinLike":30,
			"pinSocialitem":3000,
			"pinProtrait":"img/b1.jpg",
			"width":474,
			"height":675
		},
		{
			"pinUrl": "img/10.jpg",
			"pinTitle": "The 'UI'",
			"pinDescription":"",
			"pinAttribution":"Apartment Therapy",
			"pinSourceType" :"UI",
			"pinIdType":"4",
			"pinPiked":"true",
			"pinCreditsname":"AJ",
			"pinLike":30,
			"pinSocialitem":3000,
			"pinProtrait":"img/b1.jpg",
			"width":474,
			"height":808
		},
		{
			"pinUrl": "img/11.jpg",
			"pinTitle": "The 'ART'",
			"pinDescription":"some fair art",
			"pinAttribution":"Apartment Therapy",
			"pinSourceType" :"Art & originalty",
			"pinIdType":"7",
			"pinPiked":"true",
			"pinCreditsname":"AJ",
			"pinLike":30,
			"pinSocialitem":3000,
			"pinProtrait":"img/b1.jpg",
			"width":474,
			"height":1192
		}
	]
}